{
"type": "FeatureCollection",
"crs": { "type": "name", "properties": { "name": "urn:ogc:def:crs:OGC:1.3:CRS84" } },
                                                                                
"features": [
{ "type": "Feature", "properties": { "Id": null, "nom": "Maison des associations" }, "geometry": { "type": "Point", "coordinates": [ 3.511230827292215, 50.353398281448591 ] } }
]
}
